pao/__init__.py
pao/common/__init__.py
pao/common/shellcmd.py
pao/common/solver.py
pao/common/tests/__init__.py
pao/common/tests/test_solver.py
pao/mpr/__init__.py
pao/mpr/convert_repn.py
pao/mpr/repn.py
pao/mpr/soln_manager.py
pao/mpr/solver.py
pao/mpr/examples/__init__.py
pao/mpr/examples/anadalingam.py
pao/mpr/examples/bard511.py
pao/mpr/examples/bard511_list.py
pao/mpr/examples/barguel.py
pao/mpr/examples/besancon27.py
pao/mpr/examples/besancon27_shifted.py
pao/mpr/examples/getachew_ex1.py
pao/mpr/examples/getachew_ex2.py
pao/mpr/examples/mibs.py
pao/mpr/examples/moore.py
pao/mpr/examples/pao1.py
pao/mpr/examples/pao2.py
pao/mpr/examples/pao3.py
pao/mpr/examples/pineda.py
pao/mpr/examples/toyexample1.py
pao/mpr/examples/toyexample2.py
pao/mpr/examples/toyexample3.py
pao/mpr/solvers/__init__.py
pao/mpr/solvers/fa.py
pao/mpr/solvers/ld.py
pao/mpr/solvers/mibs.py
pao/mpr/solvers/pccg.py
pao/mpr/solvers/pccg_solver.py
pao/mpr/solvers/pyomo_util.py
pao/mpr/solvers/reg.py
pao/pyomo/__init__.py
pao/pyomo/components.py
pao/pyomo/convert.py
pao/pyomo/solver.py
pao/pyomo/util.py
pao/pyomo/examples/__init__.py
pao/pyomo/examples/anadalingam.py
pao/pyomo/examples/bard511.py
pao/pyomo/examples/barguel.py
pao/pyomo/examples/besancon27.py
pao/pyomo/examples/gecco2013.py
pao/pyomo/examples/getachew_ex1.py
pao/pyomo/examples/getachew_ex2.py
pao/pyomo/examples/mibs.py
pao/pyomo/examples/moore.py
pao/pyomo/examples/pao1.py
pao/pyomo/examples/pao2.py
pao/pyomo/examples/pao3.py
pao/pyomo/examples/pineda.py
pao/pyomo/examples/sip_example1.py
pao/pyomo/examples/toyexample1.py
pao/pyomo/examples/toyexample2.py
pao/pyomo/examples/toyexample3.py
pao/pyomo/plugins/__init__.py
pao/pyomo/plugins/collect.py
pao/pyomo/plugins/dual.py
pao/pyomo/plugins/highpoint.py
pao/pyomo/plugins/lcp.py
pao/pyomo/plugins/transform.py
pao/pyomo/solvers/__init__.py
pao/pyomo/solvers/mpr_solvers.py
pao/pyomo/solvers/solver_helpers.py
pao/pyomo/solvers/solver_utils.py
pao/pyomo/tests/__init__.py
pao-1.0.1.dist-info/LICENSE.txt
pao-1.0.1.dist-info/METADATA
pao-1.0.1.dist-info/WHEEL
pao-1.0.1.dist-info/top_level.txt
pao-1.0.1.dist-info/RECORD
